vixf.py
vixf-0.0.1.dist-info/LICENSE
vixf-0.0.1.dist-info/METADATA
vixf-0.0.1.dist-info/WHEEL
vixf-0.0.1.dist-info/entry_points.txt
vixf-0.0.1.dist-info/top_level.txt
vixf-0.0.1.dist-info/RECORD
